core_console/__init__.py
core_console/test.py
core_console-0.1.0.dist-info/METADATA
core_console-0.1.0.dist-info/WHEEL
core_console-0.1.0.dist-info/RECORD
